guide_search/__about__.py
guide_search/__init__.py
guide_search/cache.py
guide_search/dsl.py
guide_search/esearch.py
guide_search/exceptions.py
guide_search-0.0.141.dist-info/DESCRIPTION.rst
guide_search-0.0.141.dist-info/METADATA
guide_search-0.0.141.dist-info/RECORD
guide_search-0.0.141.dist-info/WHEEL
guide_search-0.0.141.dist-info/metadata.json
guide_search-0.0.141.dist-info/top_level.txt
