Metadata-Version: 2.0
Name: guide-search
Version: 0.0.141
Summary: Guidance management api
Home-page: https://github.com/johnpickerill/guide-search
Author: John Pickerill
Author-email: john.pickerill@landregistry.gov.uk
License: MIT
Platform: any
Classifier: Development Status :: 4 - Beta
Classifier: Environment :: Web Environment
Classifier: Intended Audience :: Developers
Classifier: License :: OSI Approved :: BSD License
Classifier: Operating System :: OS Independent
Classifier: Programming Language :: Python
Classifier: Programming Language :: Python :: 2.7
Classifier: Programming Language :: Python :: 3.5
Classifier: Programming Language :: Python :: Implementation :: PyPy
Classifier: Topic :: Software Development :: Libraries :: Python Modules
Requires-Dist: requests
